pyrclone/__init__.py
pyrclone/rclone
pyrclone/rclone_wrapper.py
pyrclone_wrapper-0.0.3.dist-info/LICENSE
pyrclone_wrapper-0.0.3.dist-info/METADATA
pyrclone_wrapper-0.0.3.dist-info/WHEEL
pyrclone_wrapper-0.0.3.dist-info/top_level.txt
pyrclone_wrapper-0.0.3.dist-info/RECORD
