Metadata-Version: 2.1
Name: pyrclone-wrapper
Version: 0.0.3
Summary: A package that provides a wrapper for RClone
Home-page: https://github.com/DeepUSC/rclone-wrapper
Author: Yuangang Li
Classifier: Programming Language :: Python :: 3
Classifier: License :: OSI Approved :: MIT License
Classifier: Operating System :: OS Independent
Requires-Python: >=3.6
License-File: LICENSE
